lidar2d_fast.cpython-38-x86_64-linux-gnu.so
highrl-1.4.0.dist-info/top_level.txt
highrl-1.4.0.dist-info/LICENSE
highrl-1.4.0.dist-info/RECORD
highrl-1.4.0.dist-info/WHEEL
highrl-1.4.0.dist-info/METADATA
highrl-1.4.0.dist-info/entry_points.txt
highrl/__main__.py
highrl/__init__.py
highrl/graphs/model_training_plot_styles.py
highrl/graphs/__init__.py
highrl/graphs/plot_using_max_of_points.py
highrl/graphs/plot_using_averages.py
highrl/graphs/plot_using_smoothing.py
highrl/graphs/plot_using_min_of_points.py
highrl/configs/__init__.py
highrl/configs/configurations.py
highrl/configs/colors.py
highrl/callbacks/teacher_callback.py
highrl/callbacks/robot_callback.py
highrl/callbacks/__init__.py
highrl/obstacle/obstacles.py
highrl/obstacle/__init__.py
highrl/obstacle/single_obstacle.py
highrl/envs/__init__.py
highrl/envs/eval_env.py
highrl/envs/env_encoders.py
highrl/envs/teacher_env.py
highrl/envs/robot_env.py
highrl/agents/robot.py
highrl/agents/__init_.py
highrl/agents/agent.py
highrl/utils/teacher_utils.py
highrl/utils/training_utils.py
highrl/utils/logger.py
highrl/utils/__init__.py
highrl/utils/parser.py
highrl/utils/action.py
highrl/utils/teacher_checker.py
highrl/utils/calculations.py
highrl/utils/robot_utils.py
highrl/utils/abstract.py
highrl/utils/general.py
highrl/lidar_setup/__init__.py
highrl/lidar_setup/rings.py
highrl/policy/__init__.py
highrl/policy/policy_networks.py
highrl/policy/feature_extractors.py
