Metadata-Version: 2.1
Name: highrl
Version: 1.4.0
Summary: Two level RL for robots navigation
Author-email: Ahmed Heakl <ahmed.heakl@ejust.edu.eg>
Project-URL: repository, https://github.com/ahmedheakl/multi-level-rl-for-robotics
Keywords: reinforcement learning,robots,robot navigation,hierarchical reinforcement learning
Classifier: License :: OSI Approved :: MIT License
Classifier: Programming Language :: Python
Classifier: Programming Language :: Python :: 3
Requires-Python: >=3.7
License-File: LICENSE
Requires-Dist: Cython (>=0.29.32)
Requires-Dist: gym (==0.21.0)
Requires-Dist: numpy (>=1.21.0)
Requires-Dist: pandas (>=1.3.5)
Requires-Dist: prettytable (>=3.5.0)
Requires-Dist: pyglet (==1.5.26)
Requires-Dist: pymap2d (>=0.1.15)
Requires-Dist: rich-argparse (>=0.5.0)
Requires-Dist: setuptools (>=45.2.0)
Requires-Dist: stable-baselines3 (>=1.6.0)
Requires-Dist: torch (>=1.12.1)
Requires-Dist: tensorboard (>=2.12.0)
Requires-Dist: coloredlogs
Provides-Extra: build
Requires-Dist: build ; extra == 'build'
Requires-Dist: twine ; extra == 'build'
Provides-Extra: dev
Requires-Dist: black ; extra == 'dev'
Requires-Dist: bumpver ; extra == 'dev'
